LICENSE
MANIFEST.in
README.rst
setup.cfg
setup.py
bagou/__init__.py
bagou/channel.py
bagou/client.py
bagou/events.py
bagou/exceptions.py
bagou/handler.py
bagou/models.py
bagou/server.py
bagou/management/__init__.py
bagou/management/commands/__init__.py
bagou/management/commands/runwebsocket.py
bagou/static/js/bagou.js
bagou/static/js/uuid.js
bagou/templates/bagou_scripts.html
bagou/templatetags/__init__.py
bagou/templatetags/bagou_tags.py
bagou/utils/__init__.py
bagou/utils/message.py
django_bagou.egg-info/PKG-INFO
django_bagou.egg-info/SOURCES.txt
django_bagou.egg-info/dependency_links.txt
django_bagou.egg-info/requires.txt
django_bagou.egg-info/top_level.txt
docs/Makefile
docs/conf.py
docs/index.rst
docs/make.bat
docs/requirements.txt
docs/_templates/sidebarintro.html
docs/_templates/sidebarlogo.html
docs/_themes/LICENSE
docs/_themes/README.rst
docs/_themes/flask_theme_support.py
docs/_themes/kr/layout.html
docs/_themes/kr/relations.html
docs/_themes/kr/theme.conf
docs/_themes/kr/static/flasky.css_t
docs/_themes/kr_small/layout.html
docs/_themes/kr_small/theme.conf
docs/_themes/kr_small/static/flasky.css_t
docs/api/events.rst
docs/user/authentication.rst
docs/user/configuration.rst
docs/user/examples.rst
docs/user/install.rst
docs/user/intro.rst